<?xml version="1.0" encoding="UTF-8"?><!--Dummy comment--><link:linkbase xmlns="http://www.xbrl.org/2003/linkbase" xmlns:ifrs_im="https://xbrl.ifrs.org/taxonomy/2022-05-25/ifrs_im" xmlns:link="http://www.xbrl.org/2003/linkbase" xmlns:xlink="http://www.w3.org/1999/xlink">
  <link:roleRef roleURI="https://xbrl.ifrs.org/role/ifrs_im/im_1-2022-05-25_role-825300" xlink:href="rol_ifrs_im1_2022-05-25.xsd#im_1-2022-05-25_role-825300" xlink:type="simple"/>
  <link:presentationLink xlink:role="https://xbrl.ifrs.org/role/ifrs_im/im_1-2022-05-25_role-825300" xlink:type="extended">
    <link:loc xlink:href="../../ifrs_im-cor_2022-05-25.xsd#ifrs-im_EnergyManagementDisclosureTextBlock" xlink:label="loc_2" xlink:title="EnergyManagementDisclosureTextBlock" xlink:type="locator"/>
    <link:loc xlink:href="../../ifrs_im-cor_2022-05-25.xsd#ifrs-im_EnergyManagementDisclosureAbstract" xlink:label="loc_1" xlink:title="EnergyManagementDisclosureAbstract" xlink:type="locator"/>
    <link:presentationArc order="10.0" priority="0" use="optional" xlink:arcrole="http://www.xbrl.org/2003/arcrole/parent-child" xlink:from="loc_1" xlink:title="presentation: EnergyManagementDisclosureAbstract to EnergyManagementDisclosureTextBlock" xlink:to="loc_2" xlink:type="arc"/>
    <link:loc xlink:href="../../ifrs_im-cor_2022-05-25.xsd#ifrs-im_EnergySourceAxis" xlink:label="loc_4" xlink:title="EnergySourceAxis" xlink:type="locator"/>
    <link:loc xlink:href="../../ifrs_im-cor_2022-05-25.xsd#ifrs-im_EnergyConsumedPercentageTable" xlink:label="loc_3" xlink:title="EnergyConsumedPercentageTable" xlink:type="locator"/>
    <link:presentationArc order="10.0" priority="0" use="optional" xlink:arcrole="http://www.xbrl.org/2003/arcrole/parent-child" xlink:from="loc_3" xlink:title="presentation: EnergyConsumedPercentageTable to EnergySourceAxis" xlink:to="loc_4" xlink:type="arc"/>
    <link:loc xlink:href="../../ifrs_im-cor_2022-05-25.xsd#ifrs-im_EnergySourceDomain" xlink:label="loc_5" xlink:title="EnergySourceDomain" xlink:type="locator"/>
    <link:presentationArc order="10.0" priority="0" use="optional" xlink:arcrole="http://www.xbrl.org/2003/arcrole/parent-child" xlink:from="loc_4" xlink:title="presentation: EnergySourceAxis to EnergySourceDomain" xlink:to="loc_5" xlink:type="arc"/>
    <link:loc xlink:href="../../ifrs_im-cor_2022-05-25.xsd#ifrs-im_GridElectricityMember" xlink:label="loc_6" xlink:title="GridElectricityMember" xlink:type="locator"/>
    <link:presentationArc order="10.0" priority="0" use="optional" xlink:arcrole="http://www.xbrl.org/2003/arcrole/parent-child" xlink:from="loc_5" xlink:title="presentation: EnergySourceDomain to GridElectricityMember" xlink:to="loc_6" xlink:type="arc"/>
    <link:loc xlink:href="../../ifrs_im-cor_2022-05-25.xsd#ifrs-im_EnergyConsumedPercentage" xlink:label="loc_9" xlink:title="EnergyConsumedPercentage" xlink:type="locator"/>
    <link:loc xlink:href="../../ifrs_im-cor_2022-05-25.xsd#ifrs-im_EnergyConsumedPercentageLineItems" xlink:label="loc_8" xlink:title="EnergyConsumedPercentageLineItems" xlink:type="locator"/>
    <link:presentationArc order="10.0" priority="0" use="optional" xlink:arcrole="http://www.xbrl.org/2003/arcrole/parent-child" xlink:from="loc_8" xlink:title="presentation: EnergyConsumedPercentageLineItems to EnergyConsumedPercentage" xlink:to="loc_9" xlink:type="arc"/>
    <link:loc xlink:href="../../ifrs_im-cor_2022-05-25.xsd#ifrs-im_EnergyConsumedPercentageAbstract" xlink:label="loc_11" xlink:title="EnergyConsumedPercentageAbstract5326" xlink:type="locator"/>
    <link:loc xlink:href="../../ifrs_im-cor_2022-05-25.xsd#ifrs-im_HCDY130a1Abstract" xlink:label="loc_10" xlink:title="HCDY130a1Abstract" xlink:type="locator"/>
    <link:presentationArc order="10.0" priority="0" use="optional" xlink:arcrole="http://www.xbrl.org/2003/arcrole/parent-child" xlink:from="loc_10" xlink:title="presentation: HCDY130a1Abstract to EnergyConsumedPercentageAbstract" xlink:to="loc_11" xlink:type="arc"/>
    <link:presentationArc order="10.0" xlink:arcrole="http://www.xbrl.org/2003/arcrole/parent-child" xlink:from="loc_11" xlink:title="presentation: EnergyConsumedPercentageAbstract to EnergyConsumedPercentageTable" xlink:to="loc_3" xlink:type="arc"/>
    <link:loc xlink:href="../../ifrs_im-cor_2022-05-25.xsd#ifrs-im_FacilityTypeAxis" xlink:label="loc_14" xlink:title="FacilityTypeAxis" xlink:type="locator"/>
    <link:loc xlink:href="../../ifrs_im-cor_2022-05-25.xsd#ifrs-im_FacilitiesNumberTable" xlink:label="loc_13" xlink:title="FacilitiesNumberTable" xlink:type="locator"/>
    <link:presentationArc order="10.0" priority="0" use="optional" xlink:arcrole="http://www.xbrl.org/2003/arcrole/parent-child" xlink:from="loc_13" xlink:title="presentation: FacilitiesNumberTable to FacilityTypeAxis" xlink:to="loc_14" xlink:type="arc"/>
    <link:loc xlink:href="../../ifrs_im-cor_2022-05-25.xsd#ifrs-im_FacilityTypeDomain" xlink:label="loc_15" xlink:title="FacilityTypeDomain" xlink:type="locator"/>
    <link:presentationArc order="10.0" priority="0" use="optional" xlink:arcrole="http://www.xbrl.org/2003/arcrole/parent-child" xlink:from="loc_14" xlink:title="presentation: FacilityTypeAxis to FacilityTypeDomain" xlink:to="loc_15" xlink:type="arc"/>
    <link:loc xlink:href="../../ifrs_im-cor_2022-05-25.xsd#ifrs-im_GeneralAcuteCareFacilityMember" xlink:label="loc_16" xlink:title="GeneralAcuteCareFacilityMember" xlink:type="locator"/>
    <link:presentationArc order="10.0" priority="0" use="optional" xlink:arcrole="http://www.xbrl.org/2003/arcrole/parent-child" xlink:from="loc_15" xlink:title="presentation: FacilityTypeDomain to GeneralAcuteCareFacilityMember" xlink:to="loc_16" xlink:type="arc"/>
    <link:loc xlink:href="../../ifrs_im-cor_2022-05-25.xsd#ifrs-im_FacilitiesNumber" xlink:label="loc_21" xlink:title="FacilitiesNumber" xlink:type="locator"/>
    <link:loc xlink:href="../../ifrs_im-cor_2022-05-25.xsd#ifrs-im_FacilitiesNumberLineItems" xlink:label="loc_20" xlink:title="FacilitiesNumberLineItems" xlink:type="locator"/>
    <link:presentationArc order="10.0" priority="0" use="optional" xlink:arcrole="http://www.xbrl.org/2003/arcrole/parent-child" xlink:from="loc_20" xlink:title="presentation: FacilitiesNumberLineItems to FacilitiesNumber" xlink:to="loc_21" xlink:type="arc"/>
    <link:loc xlink:href="../../ifrs_im-cor_2022-05-25.xsd#ifrs-im_WasteManagementDisclosureTextBlock" xlink:label="loc_23" xlink:title="WasteManagementDisclosureTextBlock" xlink:type="locator"/>
    <link:loc xlink:href="../../ifrs_im-cor_2022-05-25.xsd#ifrs-im_WasteManagementDisclosureAbstract" xlink:label="loc_22" xlink:title="WasteManagementDisclosureAbstract" xlink:type="locator"/>
    <link:presentationArc order="10.0" priority="0" use="optional" xlink:arcrole="http://www.xbrl.org/2003/arcrole/parent-child" xlink:from="loc_22" xlink:title="presentation: WasteManagementDisclosureAbstract to WasteManagementDisclosureTextBlock" xlink:to="loc_23" xlink:type="arc"/>
    <link:loc xlink:href="../../ifrs_im-cor_2022-05-25.xsd#ifrs-im_WasteAxis" xlink:label="loc_25" xlink:title="WasteAxis" xlink:type="locator"/>
    <link:loc xlink:href="../../ifrs_im-cor_2022-05-25.xsd#ifrs-im_WastePercentageRecycledTable" xlink:label="loc_24" xlink:title="WastePercentageRecycledTable" xlink:type="locator"/>
    <link:presentationArc order="10.0" priority="0" use="optional" xlink:arcrole="http://www.xbrl.org/2003/arcrole/parent-child" xlink:from="loc_24" xlink:title="presentation: WastePercentageRecycledTable to WasteAxis" xlink:to="loc_25" xlink:type="arc"/>
    <link:loc xlink:href="../../ifrs_im-cor_2022-05-25.xsd#ifrs-im_WasteDomain" xlink:label="loc_26" xlink:title="WasteDomain" xlink:type="locator"/>
    <link:presentationArc order="10.0" priority="0" use="optional" xlink:arcrole="http://www.xbrl.org/2003/arcrole/parent-child" xlink:from="loc_25" xlink:title="presentation: WasteAxis to WasteDomain" xlink:to="loc_26" xlink:type="arc"/>
    <link:loc xlink:href="../../ifrs_im-cor_2022-05-25.xsd#ifrs-im_HazardousPharmaceuticalWasteMember" xlink:label="loc_27" xlink:title="HazardousPharmaceuticalWasteMember" xlink:type="locator"/>
    <link:presentationArc order="10.0" priority="0" use="optional" xlink:arcrole="http://www.xbrl.org/2003/arcrole/parent-child" xlink:from="loc_26" xlink:title="presentation: WasteDomain to HazardousPharmaceuticalWasteMember" xlink:to="loc_27" xlink:type="arc"/>
    <link:loc xlink:href="../../ifrs_im-cor_2022-05-25.xsd#ifrs-im_WastePercentageRecycled" xlink:label="loc_31" xlink:title="WastePercentageRecycled" xlink:type="locator"/>
    <link:loc xlink:href="../../ifrs_im-cor_2022-05-25.xsd#ifrs-im_WastePercentageRecycledLineItems" xlink:label="loc_30" xlink:title="WastePercentageRecycledLineItems" xlink:type="locator"/>
    <link:presentationArc order="10.0" priority="0" use="optional" xlink:arcrole="http://www.xbrl.org/2003/arcrole/parent-child" xlink:from="loc_30" xlink:title="presentation: WastePercentageRecycledLineItems to WastePercentageRecycled" xlink:to="loc_31" xlink:type="arc"/>
    <link:loc xlink:href="../../ifrs_im-cor_2022-05-25.xsd#ifrs-im_WasteQuantityGeneratedTable" xlink:label="loc_32" xlink:title="WasteQuantityGeneratedTable" xlink:type="locator"/>
    <link:presentationArc order="10.0" priority="0" use="optional" xlink:arcrole="http://www.xbrl.org/2003/arcrole/parent-child" xlink:from="loc_32" xlink:title="presentation: WasteQuantityGeneratedTable to WasteAxis" xlink:to="loc_25" xlink:type="arc"/>
    <link:loc xlink:href="../../ifrs_im-cor_2022-05-25.xsd#ifrs-im_WasteQuantityGenerated" xlink:label="loc_34" xlink:title="WasteQuantityGenerated" xlink:type="locator"/>
    <link:loc xlink:href="../../ifrs_im-cor_2022-05-25.xsd#ifrs-im_WasteQuantityGeneratedLineItems" xlink:label="loc_33" xlink:title="WasteQuantityGeneratedLineItems" xlink:type="locator"/>
    <link:presentationArc order="10.0" priority="0" use="optional" xlink:arcrole="http://www.xbrl.org/2003/arcrole/parent-child" xlink:from="loc_33" xlink:title="presentation: WasteQuantityGeneratedLineItems to WasteQuantityGenerated" xlink:to="loc_34" xlink:type="arc"/>
    <link:loc xlink:href="../../ifrs_im-cor_2022-05-25.xsd#ifrs-im_WastePercentageIncineratedAbstract" xlink:label="loc_37" xlink:title="WastePercentageIncineratedAbstract5390" xlink:type="locator"/>
    <link:loc xlink:href="../../ifrs_im-cor_2022-05-25.xsd#ifrs-im_HCDY150a1Abstract" xlink:label="loc_35" xlink:title="HCDY150a1Abstract" xlink:type="locator"/>
    <link:presentationArc order="10.0" priority="0" use="optional" xlink:arcrole="http://www.xbrl.org/2003/arcrole/parent-child" xlink:from="loc_35" xlink:title="presentation: HCDY150a1Abstract to WastePercentageIncineratedAbstract" xlink:to="loc_37" xlink:type="arc"/>
    <link:loc xlink:href="../../ifrs_im-cor_2022-05-25.xsd#ifrs-im_WastePercentageIncineratedTable" xlink:label="loc_36" xlink:title="WastePercentageIncineratedTable" xlink:type="locator"/>
    <link:presentationArc order="10.0" xlink:arcrole="http://www.xbrl.org/2003/arcrole/parent-child" xlink:from="loc_37" xlink:title="presentation: WastePercentageIncineratedAbstract to WastePercentageIncineratedTable" xlink:to="loc_36" xlink:type="arc"/>
    <link:presentationArc order="10.0" priority="0" use="optional" xlink:arcrole="http://www.xbrl.org/2003/arcrole/parent-child" xlink:from="loc_36" xlink:title="presentation: WastePercentageIncineratedTable to WasteAxis" xlink:to="loc_25" xlink:type="arc"/>
    <link:loc xlink:href="../../ifrs_im-cor_2022-05-25.xsd#ifrs-im_WastePercentageIncinerated" xlink:label="loc_39" xlink:title="WastePercentageIncinerated" xlink:type="locator"/>
    <link:loc xlink:href="../../ifrs_im-cor_2022-05-25.xsd#ifrs-im_WastePercentageIncineratedLineItems" xlink:label="loc_38" xlink:title="WastePercentageIncineratedLineItems" xlink:type="locator"/>
    <link:presentationArc order="10.0" priority="0" use="optional" xlink:arcrole="http://www.xbrl.org/2003/arcrole/parent-child" xlink:from="loc_38" xlink:title="presentation: WastePercentageIncineratedLineItems to WastePercentageIncinerated" xlink:to="loc_39" xlink:type="arc"/>
    <link:loc xlink:href="../../ifrs_im-cor_2022-05-25.xsd#ifrs-im_WastePercentageLandfilledTable" xlink:label="loc_40" xlink:title="WastePercentageLandfilledTable" xlink:type="locator"/>
    <link:loc xlink:href="../../ifrs_im-cor_2022-05-25.xsd#ifrs-im_WastePercentageLandfilledAbstract" xlink:label="loc_41" xlink:title="WastePercentageLandfilledAbstract5393" xlink:type="locator"/>
    <link:presentationArc order="10.0" xlink:arcrole="http://www.xbrl.org/2003/arcrole/parent-child" xlink:from="loc_41" xlink:title="presentation: WastePercentageLandfilledAbstract to WastePercentageLandfilledTable" xlink:to="loc_40" xlink:type="arc"/>
    <link:presentationArc order="10.0" priority="0" use="optional" xlink:arcrole="http://www.xbrl.org/2003/arcrole/parent-child" xlink:from="loc_40" xlink:title="presentation: WastePercentageLandfilledTable to WasteAxis" xlink:to="loc_25" xlink:type="arc"/>
    <link:loc xlink:href="../../ifrs_im-cor_2022-05-25.xsd#ifrs-im_WastePercentageLandfilled" xlink:label="loc_43" xlink:title="WastePercentageLandfilled" xlink:type="locator"/>
    <link:loc xlink:href="../../ifrs_im-cor_2022-05-25.xsd#ifrs-im_WastePercentageLandfilledLineItems" xlink:label="loc_42" xlink:title="WastePercentageLandfilledLineItems" xlink:type="locator"/>
    <link:presentationArc order="10.0" priority="0" use="optional" xlink:arcrole="http://www.xbrl.org/2003/arcrole/parent-child" xlink:from="loc_42" xlink:title="presentation: WastePercentageLandfilledLineItems to WastePercentageLandfilled" xlink:to="loc_43" xlink:type="arc"/>
    <link:loc xlink:href="../../ifrs_im-cor_2022-05-25.xsd#ifrs-im_WastePercentageRecycledAbstract" xlink:label="loc_44" xlink:title="WastePercentageRecycledAbstract5397" xlink:type="locator"/>
    <link:presentationArc order="10.0" xlink:arcrole="http://www.xbrl.org/2003/arcrole/parent-child" xlink:from="loc_44" xlink:title="presentation: WastePercentageRecycledAbstract to WastePercentageRecycledTable" xlink:to="loc_24" xlink:type="arc"/>
    <link:loc xlink:href="../../ifrs_im-cor_2022-05-25.xsd#ifrs-im_WasteQuantityGeneratedAbstract" xlink:label="loc_45" xlink:title="WasteQuantityGeneratedAbstract5400" xlink:type="locator"/>
    <link:presentationArc order="10.0" xlink:arcrole="http://www.xbrl.org/2003/arcrole/parent-child" xlink:from="loc_45" xlink:title="presentation: WasteQuantityGeneratedAbstract to WasteQuantityGeneratedTable" xlink:to="loc_32" xlink:type="arc"/>
    <link:loc xlink:href="../../ifrs_im-cor_2022-05-25.xsd#ifrs-im_HCDY150a2Abstract" xlink:label="loc_46" xlink:title="HCDY150a2Abstract" xlink:type="locator"/>
    <link:presentationArc order="10.0" priority="0" use="optional" xlink:arcrole="http://www.xbrl.org/2003/arcrole/parent-child" xlink:from="loc_46" xlink:title="presentation: HCDY150a2Abstract to WastePercentageIncineratedAbstract" xlink:to="loc_37" xlink:type="arc"/>
    <link:loc xlink:href="../../ifrs_im-cor_2022-05-25.xsd#ifrs-im_HealthCareDeliveryIndustrySustainabilityDisclosureMetricsAbstract" xlink:label="loc_48" xlink:title="HealthCareDeliveryIndustrySustainabilityDisclosureMetricsAbstract" xlink:type="locator"/>
    <link:loc xlink:href="../../ifrs_im-cor_2022-05-25.xsd#ifrs-im_HealthCareDeliveryIndustryAbstract" xlink:label="loc_47" xlink:title="HealthCareDeliveryIndustryAbstract" xlink:type="locator"/>
    <link:presentationArc order="10.0" priority="0" use="optional" xlink:arcrole="http://www.xbrl.org/2003/arcrole/parent-child" xlink:from="loc_47" xlink:title="presentation: HealthCareDeliveryIndustryAbstract to HealthCareDeliveryIndustrySustainabilityDisclosureMetricsAbstract" xlink:to="loc_48" xlink:type="arc"/>
    <link:presentationArc order="10.0" priority="0" use="optional" xlink:arcrole="http://www.xbrl.org/2003/arcrole/parent-child" xlink:from="loc_48" xlink:title="presentation: HealthCareDeliveryIndustrySustainabilityDisclosureMetricsAbstract to EnergyManagementDisclosureAbstract" xlink:to="loc_1" xlink:type="arc"/>
    <link:loc xlink:href="../../ifrs_im-cor_2022-05-25.xsd#ifrs-im_ClimateChangeImpactsOnHumanHealthAndInfrastructureDisclosureTextBlock" xlink:label="loc_50" xlink:title="ClimateChangeImpactsOnHumanHealthAndInfrastructureDisclosureTextBlock" xlink:type="locator"/>
    <link:loc xlink:href="../../ifrs_im-cor_2022-05-25.xsd#ifrs-im_ClimateChangeImpactsOnHumanHealthAndInfrastructureDisclosureAbstract" xlink:label="loc_49" xlink:title="ClimateChangeImpactsOnHumanHealthAndInfrastructureDisclosureAbstract" xlink:type="locator"/>
    <link:presentationArc order="10.0" priority="0" use="optional" xlink:arcrole="http://www.xbrl.org/2003/arcrole/parent-child" xlink:from="loc_49" xlink:title="presentation: ClimateChangeImpactsOnHumanHealthAndInfrastructureDisclosureAbstract to ClimateChangeImpactsOnHumanHealthAndInfrastructureDisclosureTextBlock" xlink:to="loc_50" xlink:type="arc"/>
    <link:loc xlink:href="../../ifrs_im-cor_2022-05-25.xsd#ifrs-im_PoliciesAndPracticesToAddressPhysicalRisksDueToAnIncreasedFrequencyAndIntensityOfExtremeWeatherEventsTextBlock" xlink:label="loc_52" xlink:title="PoliciesAndPracticesToAddressPhysicalRisksDueToAnIncreasedFrequencyAndIntensityOfExtremeWeatherEventsTextBlock" xlink:type="locator"/>
    <link:loc xlink:href="../../ifrs_im-cor_2022-05-25.xsd#ifrs-im_HCDY450a1Abstract" xlink:label="loc_51" xlink:title="HCDY450a1Abstract" xlink:type="locator"/>
    <link:presentationArc order="10.0" priority="0" use="optional" xlink:arcrole="http://www.xbrl.org/2003/arcrole/parent-child" xlink:from="loc_51" xlink:title="presentation: HCDY450a1Abstract to PoliciesAndPracticesToAddressPhysicalRisksDueToAnIncreasedFrequencyAndIntensityOfExtremeWeatherEventsTextBlock" xlink:to="loc_52" xlink:type="arc"/>
    <link:loc xlink:href="../../ifrs_im-cor_2022-05-25.xsd#ifrs-im_HealthCareFacilitiesPercentageThatComplyWithCentersForMedicareAndMedicaidServicesEmergencyPreparednessRule" xlink:label="loc_55" xlink:title="HealthCareFacilitiesPercentageThatComplyWithCentersForMedicareAndMedicaidServicesEmergencyPreparednessRule" xlink:type="locator"/>
    <link:loc xlink:href="../../ifrs_im-cor_2022-05-25.xsd#ifrs-im_HCDY450a2Abstract" xlink:label="loc_54" xlink:title="HCDY450a2Abstract" xlink:type="locator"/>
    <link:presentationArc order="10.0" priority="0" use="optional" xlink:arcrole="http://www.xbrl.org/2003/arcrole/parent-child" xlink:from="loc_54" xlink:title="presentation: HCDY450a2Abstract to HealthCareFacilitiesPercentageThatComplyWithCentersForMedicareAndMedicaidServicesEmergencyPreparednessRule" xlink:to="loc_55" xlink:type="arc"/>
    <link:loc xlink:href="../../ifrs_im-cor_2022-05-25.xsd#ifrs-im_HCDY000AAbstract" xlink:label="loc_57" xlink:title="HCDY000AAbstract" xlink:type="locator"/>
    <link:loc xlink:href="../../ifrs_im-cor_2022-05-25.xsd#ifrs-im_HealthCareDeliveryIndustryActivityMetricsAbstract" xlink:label="loc_56" xlink:title="HealthCareDeliveryIndustryActivityMetricsAbstract" xlink:type="locator"/>
    <link:presentationArc order="10.0" xlink:arcrole="http://www.xbrl.org/2003/arcrole/parent-child" xlink:from="loc_56" xlink:title="presentation: HealthCareDeliveryIndustryActivityMetricsAbstract to HCDY000AAbstract" xlink:to="loc_57" xlink:type="arc"/>
    <link:loc xlink:href="../../ifrs_im-cor_2022-05-25.xsd#ifrs-im_BedsNumberAbstract" xlink:label="loc_59" xlink:title="BedsNumberAbstract5297" xlink:type="locator"/>
    <link:presentationArc order="10.0" xlink:arcrole="http://www.xbrl.org/2003/arcrole/parent-child" xlink:from="loc_57" xlink:title="presentation: HCDY000AAbstract to BedsNumberAbstract" xlink:to="loc_59" xlink:type="arc"/>
    <link:loc xlink:href="../../ifrs_im-cor_2022-05-25.xsd#ifrs-im_BedsNumberTable" xlink:label="loc_58" xlink:title="BedsNumberTable" xlink:type="locator"/>
    <link:presentationArc order="10.0" xlink:arcrole="http://www.xbrl.org/2003/arcrole/parent-child" xlink:from="loc_59" xlink:title="presentation: BedsNumberAbstract to BedsNumberTable" xlink:to="loc_58" xlink:type="arc"/>
    <link:presentationArc order="10.0" priority="0" use="optional" xlink:arcrole="http://www.xbrl.org/2003/arcrole/parent-child" xlink:from="loc_58" xlink:title="presentation: BedsNumberTable to FacilityTypeAxis" xlink:to="loc_14" xlink:type="arc"/>
    <link:loc xlink:href="../../ifrs_im-cor_2022-05-25.xsd#ifrs-im_BedsNumber" xlink:label="loc_61" xlink:title="BedsNumber" xlink:type="locator"/>
    <link:loc xlink:href="../../ifrs_im-cor_2022-05-25.xsd#ifrs-im_BedsNumberLineItems" xlink:label="loc_60" xlink:title="BedsNumberLineItems" xlink:type="locator"/>
    <link:presentationArc order="10.0" priority="0" use="optional" xlink:arcrole="http://www.xbrl.org/2003/arcrole/parent-child" xlink:from="loc_60" xlink:title="presentation: BedsNumberLineItems to BedsNumber" xlink:to="loc_61" xlink:type="arc"/>
    <link:loc xlink:href="../../ifrs_im-cor_2022-05-25.xsd#ifrs-im_FacilitiesNumberAbstract" xlink:label="loc_62" xlink:title="FacilitiesNumberAbstract5324" xlink:type="locator"/>
    <link:presentationArc order="10.0" xlink:arcrole="http://www.xbrl.org/2003/arcrole/parent-child" xlink:from="loc_62" xlink:title="presentation: FacilitiesNumberAbstract to FacilitiesNumberTable" xlink:to="loc_13" xlink:type="arc"/>
    <link:loc xlink:href="../../ifrs_im-cor_2022-05-25.xsd#ifrs-im_PatientsNumberAbstract" xlink:label="loc_65" xlink:title="PatientsNumberAbstract5325" xlink:type="locator"/>
    <link:loc xlink:href="../../ifrs_im-cor_2022-05-25.xsd#ifrs-im_HCDY000BAbstract" xlink:label="loc_63" xlink:title="HCDY000BAbstract" xlink:type="locator"/>
    <link:presentationArc order="10.0" priority="0" use="optional" xlink:arcrole="http://www.xbrl.org/2003/arcrole/parent-child" xlink:from="loc_63" xlink:title="presentation: HCDY000BAbstract to PatientsNumberAbstract" xlink:to="loc_65" xlink:type="arc"/>
    <link:loc xlink:href="../../ifrs_im-cor_2022-05-25.xsd#ifrs-im_PatientsNumberTable" xlink:label="loc_64" xlink:title="PatientsNumberTable" xlink:type="locator"/>
    <link:presentationArc order="10.0" xlink:arcrole="http://www.xbrl.org/2003/arcrole/parent-child" xlink:from="loc_65" xlink:title="presentation: PatientsNumberAbstract to PatientsNumberTable" xlink:to="loc_64" xlink:type="arc"/>
    <link:loc xlink:href="../../ifrs_im-cor_2022-05-25.xsd#ifrs-im_PatientTypeAxis" xlink:label="loc_66" xlink:title="PatientTypeAxis" xlink:type="locator"/>
    <link:presentationArc order="10.0" xlink:arcrole="http://www.xbrl.org/2003/arcrole/parent-child" xlink:from="loc_64" xlink:title="presentation: PatientsNumberTable to PatientTypeAxis" xlink:to="loc_66" xlink:type="arc"/>
    <link:loc xlink:href="../../ifrs_im-cor_2022-05-25.xsd#ifrs-im_PatientTypeDomain" xlink:label="loc_67" xlink:title="PatientTypeDomain" xlink:type="locator"/>
    <link:presentationArc order="10.0" priority="0" use="optional" xlink:arcrole="http://www.xbrl.org/2003/arcrole/parent-child" xlink:from="loc_66" xlink:title="presentation: PatientTypeAxis to PatientTypeDomain" xlink:to="loc_67" xlink:type="arc"/>
    <link:loc xlink:href="../../ifrs_im-cor_2022-05-25.xsd#ifrs-im_InpatientAdmissionMember" xlink:label="loc_68" xlink:title="InpatientAdmissionMember" xlink:type="locator"/>
    <link:presentationArc order="10.0" priority="0" use="optional" xlink:arcrole="http://www.xbrl.org/2003/arcrole/parent-child" xlink:from="loc_67" xlink:title="presentation: PatientTypeDomain to InpatientAdmissionMember" xlink:to="loc_68" xlink:type="arc"/>
    <link:loc xlink:href="../../ifrs_im-cor_2022-05-25.xsd#ifrs-im_PatientsNumber" xlink:label="loc_71" xlink:title="PatientsNumber" xlink:type="locator"/>
    <link:loc xlink:href="../../ifrs_im-cor_2022-05-25.xsd#ifrs-im_PatientsNumberLineItems" xlink:label="loc_70" xlink:title="PatientsNumberLineItems" xlink:type="locator"/>
    <link:presentationArc order="10.0" priority="0" use="optional" xlink:arcrole="http://www.xbrl.org/2003/arcrole/parent-child" xlink:from="loc_70" xlink:title="presentation: PatientsNumberLineItems to PatientsNumber" xlink:to="loc_71" xlink:type="arc"/>
    <link:loc xlink:href="../../ifrs_im-cor_2022-05-25.xsd#ifrs-im_RenewableEnergyMember" xlink:label="loc_7" xlink:title="RenewableEnergyMember" xlink:type="locator"/>
    <link:presentationArc order="20.0" priority="0" use="optional" xlink:arcrole="http://www.xbrl.org/2003/arcrole/parent-child" xlink:from="loc_5" xlink:title="presentation: EnergySourceDomain to RenewableEnergyMember" xlink:to="loc_7" xlink:type="arc"/>
    <link:presentationArc order="20.0" xlink:arcrole="http://www.xbrl.org/2003/arcrole/parent-child" xlink:from="loc_11" xlink:title="presentation: presentation: EnergyConsumedPercentageAbstract to EnergyConsumedPercentageLineItems" xlink:to="loc_8" xlink:type="arc"/>
    <link:presentationArc order="20.0" xlink:arcrole="http://www.xbrl.org/2003/arcrole/parent-child" xlink:from="loc_1" xlink:title="presentation: EnergyManagementDisclosureAbstract to HCDY130a1Abstract" xlink:to="loc_10" xlink:type="arc"/>
    <link:loc xlink:href="../../ifrs_im-cor_2022-05-25.xsd#ifrs-im_EnergyConsumed" xlink:label="loc_12" xlink:title="EnergyConsumed" xlink:type="locator"/>
    <link:presentationArc order="20.0" priority="0" use="optional" xlink:arcrole="http://www.xbrl.org/2003/arcrole/parent-child" xlink:from="loc_10" xlink:title="presentation: HCDY130a1Abstract to EnergyConsumed" xlink:to="loc_12" xlink:type="arc"/>
    <link:loc xlink:href="../../ifrs_im-cor_2022-05-25.xsd#ifrs-im_OutpatientCareFacilityMember" xlink:label="loc_17" xlink:title="OutpatientCareFacilityMember" xlink:type="locator"/>
    <link:presentationArc order="20.0" priority="0" use="optional" xlink:arcrole="http://www.xbrl.org/2003/arcrole/parent-child" xlink:from="loc_15" xlink:title="presentation: FacilityTypeDomain to OutpatientCareFacilityMember" xlink:to="loc_17" xlink:type="arc"/>
    <link:presentationArc order="20.0" xlink:arcrole="http://www.xbrl.org/2003/arcrole/parent-child" xlink:from="loc_62" xlink:title="presentation: presentation: FacilitiesNumberAbstract to FacilitiesNumberLineItems" xlink:to="loc_20" xlink:type="arc"/>
    <link:loc xlink:href="../../ifrs_im-cor_2022-05-25.xsd#ifrs-im_MedicalWasteMember" xlink:label="loc_28" xlink:title="MedicalWasteMember" xlink:type="locator"/>
    <link:presentationArc order="20.0" priority="0" use="optional" xlink:arcrole="http://www.xbrl.org/2003/arcrole/parent-child" xlink:from="loc_26" xlink:title="presentation: WasteDomain to MedicalWasteMember" xlink:to="loc_28" xlink:type="arc"/>
    <link:presentationArc order="20.0" xlink:arcrole="http://www.xbrl.org/2003/arcrole/parent-child" xlink:from="loc_44" xlink:title="presentation: presentation: WastePercentageRecycledAbstract to WastePercentageRecycledLineItems" xlink:to="loc_30" xlink:type="arc"/>
    <link:presentationArc order="20.0" xlink:arcrole="http://www.xbrl.org/2003/arcrole/parent-child" xlink:from="loc_45" xlink:title="presentation: presentation: WasteQuantityGeneratedAbstract to WasteQuantityGeneratedLineItems" xlink:to="loc_33" xlink:type="arc"/>
    <link:presentationArc order="20.0" xlink:arcrole="http://www.xbrl.org/2003/arcrole/parent-child" xlink:from="loc_22" xlink:title="presentation: WasteManagementDisclosureAbstract to HCDY150a1Abstract" xlink:to="loc_35" xlink:type="arc"/>
    <link:presentationArc order="20.0" xlink:arcrole="http://www.xbrl.org/2003/arcrole/parent-child" xlink:from="loc_37" xlink:title="presentation: presentation: WastePercentageIncineratedAbstract to WastePercentageIncineratedLineItems" xlink:to="loc_38" xlink:type="arc"/>
    <link:presentationArc order="20.0" priority="0" use="optional" xlink:arcrole="http://www.xbrl.org/2003/arcrole/parent-child" xlink:from="loc_35" xlink:title="presentation: HCDY150a1Abstract to WastePercentageLandfilledAbstract" xlink:to="loc_41" xlink:type="arc"/>
    <link:presentationArc order="20.0" xlink:arcrole="http://www.xbrl.org/2003/arcrole/parent-child" xlink:from="loc_41" xlink:title="presentation: presentation: WastePercentageLandfilledAbstract to WastePercentageLandfilledLineItems" xlink:to="loc_42" xlink:type="arc"/>
    <link:presentationArc order="20.0" priority="0" use="optional" xlink:arcrole="http://www.xbrl.org/2003/arcrole/parent-child" xlink:from="loc_46" xlink:title="presentation: HCDY150a2Abstract to WastePercentageLandfilledAbstract" xlink:to="loc_41" xlink:type="arc"/>
    <link:presentationArc order="20.0" priority="0" use="optional" xlink:arcrole="http://www.xbrl.org/2003/arcrole/parent-child" xlink:from="loc_48" xlink:title="presentation: HealthCareDeliveryIndustrySustainabilityDisclosureMetricsAbstract to WasteManagementDisclosureAbstract" xlink:to="loc_22" xlink:type="arc"/>
    <link:presentationArc order="20.0" xlink:arcrole="http://www.xbrl.org/2003/arcrole/parent-child" xlink:from="loc_49" xlink:title="presentation: ClimateChangeImpactsOnHumanHealthAndInfrastructureDisclosureAbstract to HCDY450a1Abstract" xlink:to="loc_51" xlink:type="arc"/>
    <link:loc xlink:href="../../ifrs_im-cor_2022-05-25.xsd#ifrs-im_PoliciesAndPracticesToAddressChangesInMorbidityAndMortalityRatesOfIllnessesAndDiseasesAssociatedWithClimateChangeTextBlock" xlink:label="loc_53" xlink:title="PoliciesAndPracticesToAddressChangesInMorbidityAndMortalityRatesOfIllnessesAndDiseasesAssociatedWithClimateChangeTextBlock" xlink:type="locator"/>
    <link:presentationArc order="20.0" priority="0" use="optional" xlink:arcrole="http://www.xbrl.org/2003/arcrole/parent-child" xlink:from="loc_51" xlink:title="presentation: HCDY450a1Abstract to PoliciesAndPracticesToAddressChangesInMorbidityAndMortalityRatesOfIllnessesAndDiseasesAssociatedWithClimateChangeTextBlock" xlink:to="loc_53" xlink:type="arc"/>
    <link:presentationArc order="20.0" priority="0" use="optional" xlink:arcrole="http://www.xbrl.org/2003/arcrole/parent-child" xlink:from="loc_47" xlink:title="presentation: HealthCareDeliveryIndustryAbstract to HealthCareDeliveryIndustryActivityMetricsAbstract" xlink:to="loc_56" xlink:type="arc"/>
    <link:presentationArc order="20.0" xlink:arcrole="http://www.xbrl.org/2003/arcrole/parent-child" xlink:from="loc_59" xlink:title="presentation: presentation: BedsNumberAbstract to BedsNumberLineItems" xlink:to="loc_60" xlink:type="arc"/>
    <link:presentationArc order="20.0" priority="0" use="optional" xlink:arcrole="http://www.xbrl.org/2003/arcrole/parent-child" xlink:from="loc_57" xlink:title="presentation: HCDY000AAbstract to FacilitiesNumberAbstract" xlink:to="loc_62" xlink:type="arc"/>
    <link:presentationArc order="20.0" xlink:arcrole="http://www.xbrl.org/2003/arcrole/parent-child" xlink:from="loc_56" xlink:title="presentation: HealthCareDeliveryIndustryActivityMetricsAbstract to HCDY000BAbstract" xlink:to="loc_63" xlink:type="arc"/>
    <link:loc xlink:href="../../ifrs_im-cor_2022-05-25.xsd#ifrs-im_OutpatientVisitsMember" xlink:label="loc_69" xlink:title="OutpatientVisitsMember" xlink:type="locator"/>
    <link:presentationArc order="20.0" priority="0" use="optional" xlink:arcrole="http://www.xbrl.org/2003/arcrole/parent-child" xlink:from="loc_67" xlink:title="presentation: PatientTypeDomain to OutpatientVisitsMember" xlink:to="loc_69" xlink:type="arc"/>
    <link:presentationArc order="20.0" xlink:arcrole="http://www.xbrl.org/2003/arcrole/parent-child" xlink:from="loc_65" xlink:title="presentation: presentation: PatientsNumberAbstract to PatientsNumberLineItems" xlink:to="loc_70" xlink:type="arc"/>
    <link:loc xlink:href="../../ifrs_im-cor_2022-05-25.xsd#ifrs-im_PsychiatricCareFacilityMember" xlink:label="loc_18" xlink:title="PsychiatricCareFacilityMember" xlink:type="locator"/>
    <link:presentationArc order="30.0" priority="0" use="optional" xlink:arcrole="http://www.xbrl.org/2003/arcrole/parent-child" xlink:from="loc_15" xlink:title="presentation: FacilityTypeDomain to PsychiatricCareFacilityMember" xlink:to="loc_18" xlink:type="arc"/>
    <link:loc xlink:href="../../ifrs_im-cor_2022-05-25.xsd#ifrs-im_NonhazardousPharmaceuticalWasteMember" xlink:label="loc_29" xlink:title="NonhazardousPharmaceuticalWasteMember" xlink:type="locator"/>
    <link:presentationArc order="30.0" priority="0" use="optional" xlink:arcrole="http://www.xbrl.org/2003/arcrole/parent-child" xlink:from="loc_26" xlink:title="presentation: WasteDomain to NonhazardousPharmaceuticalWasteMember" xlink:to="loc_29" xlink:type="arc"/>
    <link:presentationArc order="30.0" priority="0" use="optional" xlink:arcrole="http://www.xbrl.org/2003/arcrole/parent-child" xlink:from="loc_35" xlink:title="presentation: HCDY150a1Abstract to WastePercentageRecycledAbstract" xlink:to="loc_44" xlink:type="arc"/>
    <link:presentationArc order="30.0" xlink:arcrole="http://www.xbrl.org/2003/arcrole/parent-child" xlink:from="loc_22" xlink:title="presentation: WasteManagementDisclosureAbstract to HCDY150a2Abstract" xlink:to="loc_46" xlink:type="arc"/>
    <link:presentationArc order="30.0" priority="0" use="optional" xlink:arcrole="http://www.xbrl.org/2003/arcrole/parent-child" xlink:from="loc_46" xlink:title="presentation: HCDY150a2Abstract to WastePercentageRecycledAbstract" xlink:to="loc_44" xlink:type="arc"/>
    <link:presentationArc order="30.0" xlink:arcrole="http://www.xbrl.org/2003/arcrole/parent-child" xlink:from="loc_49" xlink:title="presentation: ClimateChangeImpactsOnHumanHealthAndInfrastructureDisclosureAbstract to HCDY450a2Abstract" xlink:to="loc_54" xlink:type="arc"/>
    <link:presentationArc order="30.0" xlink:arcrole="http://www.xbrl.org/2003/arcrole/parent-child" xlink:from="loc_48" xlink:title="presentation: HealthCareDeliveryIndustrySustainabilityDisclosureMetricsAbstract to ClimateChangeImpactsOnHumanHealthAndInfrastructureDisclosureAbstract" xlink:to="loc_49" xlink:type="arc"/>
    <link:loc xlink:href="../../ifrs_im-cor_2022-05-25.xsd#ifrs-im_RehabilitationCareFacilityMember" xlink:label="loc_19" xlink:title="RehabilitationCareFacilityMember" xlink:type="locator"/>
    <link:presentationArc order="40.0" priority="0" use="optional" xlink:arcrole="http://www.xbrl.org/2003/arcrole/parent-child" xlink:from="loc_15" xlink:title="presentation: FacilityTypeDomain to RehabilitationCareFacilityMember" xlink:to="loc_19" xlink:type="arc"/>
    <link:presentationArc order="40.0" priority="0" use="optional" xlink:arcrole="http://www.xbrl.org/2003/arcrole/parent-child" xlink:from="loc_35" xlink:title="presentation: HCDY150a1Abstract to WasteQuantityGeneratedAbstract" xlink:to="loc_45" xlink:type="arc"/>
    <link:presentationArc order="40.0" priority="0" use="optional" xlink:arcrole="http://www.xbrl.org/2003/arcrole/parent-child" xlink:from="loc_46" xlink:title="presentation: HCDY150a2Abstract to WasteQuantityGeneratedAbstract" xlink:to="loc_45" xlink:type="arc"/>
    <link:loc xlink:href="../../ifrs_im-cor_2022-05-25.xsd#ifrs-im_JurisdictionalStandardOrRegulationUsedToDefineHazardousPharmaceuticalWasteTextBlock" xlink:label="loc_72" xlink:type="locator"/>
    <link:presentationArc order="50.0" xlink:arcrole="http://www.xbrl.org/2003/arcrole/parent-child" xlink:from="loc_46" xlink:to="loc_72" xlink:type="arc"/>
  </link:presentationLink>
</link:linkbase>
